MonsterBot/MonsterBot.py
MonsterBot/__init__.py
MonsterBot/netpwner.py
MonsterBot-3.1.dist-info/METADATA
MonsterBot-3.1.dist-info/WHEEL
MonsterBot-3.1.dist-info/top_level.txt
MonsterBot-3.1.dist-info/RECORD
