Metadata-Version: 2.1
Name: MonsterBot
Version: 3.1
Summary: An Online chatbot librery
Home-page: https://github.com/7lMONSTERl7/networkpwner.git
Author: MONSTER
Author-email: oussamadev22@gmail.com
Classifier: Programming Language :: Python :: 3
Classifier: License :: OSI Approved :: MIT License
Classifier: Operating System :: OS Independent
Requires-Python: >=3.6
Requires-Dist: requests>=3.3
